{
  "project_info": {
    "project_number": "1089834875276",
    "project_id": "todo-app-ee82a",
    "storage_bucket": "todo-app-ee82a.appspot.com"
  },
  "client": [
    {
      "client_info": {
        "mobilesdk_app_id": "1:1089834875276:android:f37212683038f75e327ea9",
        "android_client_info": {
          "package_name": "com.example.todo_app"
        }
      },
      "oauth_client": [],
      "api_key": [
        {
          "current_key": "AIzaSyCj5uQR2EydHCU6sQFZWNWj2XBJ1HVQmPo"
        }
      ],
      "services": {
        "appinvite_service": {
          "other_platform_oauth_client": []
        }
      }
    }
  ],
  "configuration_version": "1"
}